[
  {
    "id": "flamelet",
    "nom": "Petit Flamme",
    "tier": "C",
    "element": "feu",
    "prix": 1500,
    "competences": [
      {
        "nom": "Étincelle",
        "degats": 8
      },
      {
        "nom": "Souffle Tiède",
        "degats": 5
      },
      {
        "nom": "Flamme Légère",
        "degats": 12
      }
    ]
  },
  {
    "id": "droplet",
    "nom": "Gouttelette",
    "tier": "C",
    "element": "eau",
    "prix": 1500,
    "competences": [
      {
        "nom": "Jet d'Eau",
        "degats": 8
      },
      {
        "nom": "Bulle",
        "degats": 5
      },
      {
        "nom": "Vague Mineure",
        "degats": 12
      }
    ]
  }
]